{
  "generatedAt": "2026-02-20T23:02:48.788Z",
  "componentDir": "src/components/ui/**/*.tsx",
  "components": [
    {
      "displayName": "Alert",
      "filePath": "src/components/ui/alert.tsx",
      "description": "",
      "props": {
        "title": {
          "name": "title",
          "type": "enum",
          "rawType": "enum",
          "required": false,
          "description": "Alert title",
          "isChildren": false
        },
        "severity": {
          "name": "severity",
          "type": "enum",
          "rawType": "enum",
          "values": [
            "info",
            "success",
            "warning",
            "error"
          ],
          "required": false,
          "defaultValue": "info",
          "description": "Severity level",
          "isChildren": false
        },
        "dismissible": {
          "name": "dismissible",
          "type": "boolean",
          "rawType": "enum",
          "required": false,
          "defaultValue": "false",
          "description": "Whether the alert can be dismissed",
          "isChildren": false
        }
      },
      "acceptsChildren": true
    },
    {
      "displayName": "Avatar",
      "filePath": "src/components/ui/avatar.tsx",
      "description": "",
      "props": {
        "src": {
          "name": "src",
          "type": "enum",
          "rawType": "enum",
          "required": false,
          "description": "Image URL",
          "isChildren": false
        },
        "name": {
          "name": "name",
          "type": "enum",
          "rawType": "enum",
          "required": false,
          "defaultValue": "",
          "description": "Alt text / user name (used for initials fallback)",
          "isChildren": false
        },
        "size": {
          "name": "size",
          "type": "enum",
          "rawType": "enum",
          "values": [
            "sm",
            "md",
            "lg"
          ],
          "required": false,
          "defaultValue": "md",
          "description": "Avatar size",
          "isChildren": false
        },
        "shape": {
          "name": "shape",
          "type": "enum",
          "rawType": "enum",
          "values": [
            "circle",
            "square"
          ],
          "required": false,
          "defaultValue": "circle",
          "description": "Shape variant",
          "isChildren": false
        }
      },
      "acceptsChildren": false
    },
    {
      "displayName": "Badge",
      "filePath": "src/components/ui/badge.tsx",
      "description": "",
      "props": {
        "variant": {
          "name": "variant",
          "type": "enum",
          "rawType": "enum",
          "values": [
            "default",
            "success",
            "warning",
            "error",
            "info"
          ],
          "required": false,
          "defaultValue": "default",
          "description": "Badge color variant",
          "isChildren": false
        },
        "pill": {
          "name": "pill",
          "type": "boolean",
          "rawType": "enum",
          "required": false,
          "defaultValue": "false",
          "description": "Rounded pill shape",
          "isChildren": false
        }
      },
      "acceptsChildren": true
    },
    {
      "displayName": "Button",
      "filePath": "src/components/ui/button.tsx",
      "description": "",
      "props": {
        "variant": {
          "name": "variant",
          "type": "enum",
          "rawType": "enum",
          "values": [
            "default",
            "primary",
            "secondary",
            "destructive",
            "outline",
            "ghost"
          ],
          "required": false,
          "defaultValue": "default",
          "description": "Visual style variant",
          "isChildren": false
        },
        "size": {
          "name": "size",
          "type": "enum",
          "rawType": "enum",
          "values": [
            "sm",
            "md",
            "lg"
          ],
          "required": false,
          "defaultValue": "md",
          "description": "Button size",
          "isChildren": false
        },
        "disabled": {
          "name": "disabled",
          "type": "boolean",
          "rawType": "enum",
          "required": false,
          "defaultValue": "false",
          "description": "Whether the button is disabled",
          "isChildren": false
        },
        "fullWidth": {
          "name": "fullWidth",
          "type": "boolean",
          "rawType": "enum",
          "required": false,
          "defaultValue": "false",
          "description": "Full width button",
          "isChildren": false
        }
      },
      "acceptsChildren": true
    },
    {
      "displayName": "Card",
      "filePath": "src/components/ui/card.tsx",
      "description": "",
      "props": {
        "title": {
          "name": "title",
          "type": "enum",
          "rawType": "enum",
          "required": false,
          "description": "Card title displayed in the header",
          "isChildren": false
        },
        "description": {
          "name": "description",
          "type": "enum",
          "rawType": "enum",
          "required": false,
          "description": "Optional description below the title",
          "isChildren": false
        },
        "elevated": {
          "name": "elevated",
          "type": "boolean",
          "rawType": "enum",
          "required": false,
          "defaultValue": "false",
          "description": "Whether to add a shadow",
          "isChildren": false
        },
        "padding": {
          "name": "padding",
          "type": "enum",
          "rawType": "enum",
          "values": [
            "none",
            "sm",
            "md",
            "lg"
          ],
          "required": false,
          "defaultValue": "md",
          "description": "Padding size",
          "isChildren": false
        }
      },
      "acceptsChildren": true
    },
    {
      "displayName": "CodeBlock",
      "filePath": "src/components/ui/code-block.tsx",
      "description": "",
      "props": {
        "code": {
          "name": "code",
          "type": "string",
          "rawType": "string",
          "required": true,
          "description": "The code content to display",
          "isChildren": false
        },
        "inline": {
          "name": "inline",
          "type": "boolean",
          "rawType": "enum",
          "required": false,
          "defaultValue": "false",
          "description": "Whether to show a compact inline-style block",
          "isChildren": false
        }
      },
      "acceptsChildren": false
    },
    {
      "displayName": "FeatureStep",
      "filePath": "src/components/ui/feature-step.tsx",
      "description": "",
      "props": {
        "step": {
          "name": "step",
          "type": "number",
          "rawType": "number",
          "required": true,
          "description": "Step number displayed in the circle",
          "isChildren": false
        },
        "title": {
          "name": "title",
          "type": "string",
          "rawType": "string",
          "required": true,
          "description": "Step title",
          "isChildren": false
        }
      },
      "acceptsChildren": true
    },
    {
      "displayName": "IconButton",
      "filePath": "src/components/ui/icon-button.tsx",
      "description": "",
      "props": {
        "icon": {
          "name": "icon",
          "type": "LucideIcon",
          "rawType": "LucideIcon",
          "required": true,
          "description": "Leading icon displayed before the label",
          "isChildren": false,
          "componentKind": "icon"
        },
        "trailingIcon": {
          "name": "trailingIcon",
          "type": "enum",
          "rawType": "enum",
          "required": false,
          "description": "Optional trailing icon displayed after the label",
          "isChildren": false,
          "componentKind": "icon"
        },
        "variant": {
          "name": "variant",
          "type": "enum",
          "rawType": "enum",
          "values": [
            "default",
            "primary",
            "secondary",
            "outline"
          ],
          "required": false,
          "defaultValue": "default",
          "description": "Visual style variant",
          "isChildren": false
        },
        "size": {
          "name": "size",
          "type": "enum",
          "rawType": "enum",
          "values": [
            "sm",
            "md",
            "lg"
          ],
          "required": false,
          "defaultValue": "md",
          "description": "Button size",
          "isChildren": false
        },
        "disabled": {
          "name": "disabled",
          "type": "boolean",
          "rawType": "enum",
          "required": false,
          "defaultValue": "false",
          "description": "Whether the button is disabled",
          "isChildren": false
        }
      },
      "acceptsChildren": true
    },
    {
      "displayName": "Input",
      "filePath": "src/components/ui/input.tsx",
      "description": "",
      "props": {
        "label": {
          "name": "label",
          "type": "enum",
          "rawType": "enum",
          "required": false,
          "description": "Input label displayed above the field",
          "isChildren": false
        },
        "placeholder": {
          "name": "placeholder",
          "type": "enum",
          "rawType": "enum",
          "required": false,
          "description": "Placeholder text",
          "isChildren": false
        },
        "value": {
          "name": "value",
          "type": "enum",
          "rawType": "enum",
          "required": false,
          "description": "Current value",
          "isChildren": false
        },
        "type": {
          "name": "type",
          "type": "enum",
          "rawType": "enum",
          "values": [
            "text",
            "email",
            "password",
            "url"
          ],
          "required": false,
          "defaultValue": "text",
          "description": "Input type",
          "isChildren": false
        },
        "error": {
          "name": "error",
          "type": "enum",
          "rawType": "enum",
          "required": false,
          "description": "Error message shown below the field",
          "isChildren": false
        },
        "disabled": {
          "name": "disabled",
          "type": "boolean",
          "rawType": "enum",
          "required": false,
          "defaultValue": "false",
          "description": "Whether the input is disabled",
          "isChildren": false
        },
        "required": {
          "name": "required",
          "type": "boolean",
          "rawType": "enum",
          "required": false,
          "defaultValue": "false",
          "description": "Whether the field is required",
          "isChildren": false
        }
      },
      "acceptsChildren": false
    },
    {
      "displayName": "PricingCard",
      "filePath": "src/components/ui/pricing-card.tsx",
      "description": "",
      "props": {
        "title": {
          "name": "title",
          "type": "string",
          "rawType": "string",
          "required": true,
          "description": "Tier name displayed as the card title",
          "isChildren": false
        },
        "description": {
          "name": "description",
          "type": "string",
          "rawType": "string",
          "required": true,
          "description": "Short description of the tier",
          "isChildren": false
        },
        "price": {
          "name": "price",
          "type": "string",
          "rawType": "string",
          "required": true,
          "description": "Price display text (e.g. \"$0\", \"$29/mo\")",
          "isChildren": false
        },
        "priceLabel": {
          "name": "priceLabel",
          "type": "enum",
          "rawType": "enum",
          "required": false,
          "description": "Optional label next to the price (e.g. \"still free\", \"/month\")",
          "isChildren": false
        },
        "features": {
          "name": "features",
          "type": "string[]",
          "rawType": "string[]",
          "required": true,
          "description": "List of included features, one per line",
          "isChildren": false
        },
        "highlighted": {
          "name": "highlighted",
          "type": "boolean",
          "rawType": "enum",
          "required": false,
          "defaultValue": "false",
          "description": "Whether this tier is visually highlighted",
          "isChildren": false
        }
      },
      "acceptsChildren": true
    },
    {
      "displayName": "SectionHeader",
      "filePath": "src/components/ui/section-header.tsx",
      "description": "",
      "props": {
        "title": {
          "name": "title",
          "type": "string",
          "rawType": "string",
          "required": true,
          "description": "Section title",
          "isChildren": false
        },
        "subtitle": {
          "name": "subtitle",
          "type": "enum",
          "rawType": "enum",
          "required": false,
          "description": "Optional subtitle text displayed below the title",
          "isChildren": false
        },
        "badge": {
          "name": "badge",
          "type": "enum",
          "rawType": "enum",
          "required": false,
          "description": "Optional badge content displayed above the title",
          "isChildren": false,
          "componentKind": "node"
        },
        "align": {
          "name": "align",
          "type": "enum",
          "rawType": "enum",
          "values": [
            "left",
            "center"
          ],
          "required": false,
          "defaultValue": "center",
          "description": "Text alignment",
          "isChildren": false
        }
      },
      "acceptsChildren": false
    },
    {
      "displayName": "StatCard",
      "filePath": "src/components/ui/stat-card.tsx",
      "description": "",
      "props": {
        "label": {
          "name": "label",
          "type": "string",
          "rawType": "string",
          "required": true,
          "description": "The metric label",
          "isChildren": false
        },
        "value": {
          "name": "value",
          "type": "string",
          "rawType": "string",
          "required": true,
          "description": "The metric value",
          "isChildren": false
        },
        "icon": {
          "name": "icon",
          "type": "LucideIcon",
          "rawType": "LucideIcon",
          "required": true,
          "description": "Icon displayed in the card",
          "isChildren": false,
          "componentKind": "icon"
        },
        "trend": {
          "name": "trend",
          "type": "enum",
          "rawType": "enum",
          "values": [
            "up",
            "down",
            "neutral"
          ],
          "required": false,
          "defaultValue": "neutral",
          "description": "Trend direction indicator",
          "isChildren": false
        },
        "trendText": {
          "name": "trendText",
          "type": "enum",
          "rawType": "enum",
          "required": false,
          "description": "Trend percentage text (e.g. \"+12%\")",
          "isChildren": false
        }
      },
      "acceptsChildren": false
    },
    {
      "displayName": "TestimonialCard",
      "filePath": "src/components/ui/testimonial-card.tsx",
      "description": "",
      "props": {
        "quote": {
          "name": "quote",
          "type": "string",
          "rawType": "string",
          "required": true,
          "description": "The testimonial quote text",
          "isChildren": false
        },
        "name": {
          "name": "name",
          "type": "string",
          "rawType": "string",
          "required": true,
          "description": "Author's full name",
          "isChildren": false
        },
        "role": {
          "name": "role",
          "type": "string",
          "rawType": "string",
          "required": true,
          "description": "Author's role or title",
          "isChildren": false
        }
      },
      "acceptsChildren": false
    }
  ]
}